girona_donostia/__init__.py
girona_donostia/curve_fit.py
girona_donostia/functions_for_library.py
girona_donostia/hyperpolarizabilities.py
girona_donostia/objects_for_library.py
girona_donostia/romberg.py
girona_donostia/statistic.py
girona_donostia-0.1.15.dist-info/LICENSE
girona_donostia-0.1.15.dist-info/METADATA
girona_donostia-0.1.15.dist-info/WHEEL
girona_donostia-0.1.15.dist-info/top_level.txt
girona_donostia-0.1.15.dist-info/RECORD
