Metadata-Version: 2.1
Name: girona-donostia
Version: 0.1.15
Summary: A small package to work with nonlinear optical propreties
Home-page: https://github.com/Petru-Milev/Girona_Donostia
Author: Petru Milev
Author-email: Petru Milev <petia.md36@gmail.com>
License: MIT License        
Project-URL: Homepage, https://github.com/Petru-Milev/Girona_Donostia
Classifier: Programming Language :: Python :: 3
Classifier: License :: OSI Approved :: MIT License
Classifier: Operating System :: OS Independent
Requires-Python: >=3.6
License-File: LICENSE
Requires-Dist: numpy
Requires-Dist: scipy
